{
  "node": "Count_CriminalActivities_CombinedCrime",
  "info": {
    "placeTypeSummary": {
      "CensusCountyDivision": {
        "placeCount": 1496,
        "topPlaces": [
          {
            "dcid": "geoId/1500390810",
            "name": "Honolulu CCD"
          },
          {
            "dcid": "geoId/3608760510",
            "name": "Ramapo"
          },
          {
            "dcid": "geoId/3402938550",
            "name": "Lakewood"
          }
        ],
        "minValue": 0,
        "maxValue": 36325
      },
      "City": {
        "placeCount": 9888,
        "topPlaces": [
          {
            "dcid": "geoId/3651000",
            "name": "New York"
          },
          {
            "dcid": "geoId/0644000",
            "name": "Los Angeles"
          },
          {
            "dcid": "geoId/1714000",
            "name": "Chicago"
          }
        ],
        "minValue": 0,
        "maxValue": 250958
      },
      "Country": {
        "placeCount": 1,
        "topPlaces": [
          {
            "dcid": "country/USA",
            "name": "United States"
          }
        ],
        "minValue": 7782709,
        "maxValue": 11111207
      },
      "County": {
        "placeCount": 4,
        "topPlaces": [
          {
            "dcid": "geoId/34007",
            "name": "Camden County"
          },
          {
            "dcid": "geoId/26121",
            "name": "Muskegon County"
          },
          {
            "dcid": "geoId/02185",
            "name": "North Slope Borough"
          }
        ],
        "minValue": 13,
        "maxValue": 4043
      },
      "State": {
        "placeCount": 52,
        "topPlaces": [
          {
            "dcid": "geoId/06",
            "name": "California"
          },
          {
            "dcid": "geoId/48",
            "name": "Texas"
          },
          {
            "dcid": "geoId/12",
            "name": "Florida"
          }
        ],
        "minValue": 8667,
        "maxValue": 1265920
      }
    },
    "provenanceSummary": {
      "dc/base/FBIGovCrime": {
        "importName": "FBIGovCrime",
        "releaseFrequency": "P1Y",
        "seriesSummary": [
          {
            "seriesKey": {
              "observationPeriod": "P1Y"
            },
            "earliestDate": "2008",
            "latestDate": "2023",
            "placeTypeSummary": {
              "CensusCountyDivision": {
                "placeCount": 1496,
                "topPlaces": [
                  {
                    "dcid": "geoId/1500390810",
                    "name": "Honolulu CCD"
                  },
                  {
                    "dcid": "geoId/3608760510",
                    "name": "Ramapo"
                  },
                  {
                    "dcid": "geoId/3402938550",
                    "name": "Lakewood"
                  }
                ],
                "minValue": 0,
                "maxValue": 36325
              },
              "City": {
                "placeCount": 9888,
                "topPlaces": [
                  {
                    "dcid": "geoId/3651000",
                    "name": "New York"
                  },
                  {
                    "dcid": "geoId/0644000",
                    "name": "Los Angeles"
                  },
                  {
                    "dcid": "geoId/1714000",
                    "name": "Chicago"
                  }
                ],
                "minValue": 0,
                "maxValue": 250958
              },
              "County": {
                "placeCount": 4,
                "topPlaces": [
                  {
                    "dcid": "geoId/34007",
                    "name": "Camden County"
                  },
                  {
                    "dcid": "geoId/26121",
                    "name": "Muskegon County"
                  },
                  {
                    "dcid": "geoId/02185",
                    "name": "North Slope Borough"
                  }
                ],
                "minValue": 8,
                "maxValue": 4043
              },
              "State": {
                "placeCount": 52,
                "topPlaces": [
                  {
                    "dcid": "geoId/06",
                    "name": "California"
                  },
                  {
                    "dcid": "geoId/48",
                    "name": "Texas"
                  },
                  {
                    "dcid": "geoId/12",
                    "name": "Florida"
                  }
                ],
                "minValue": 8667,
                "maxValue": 1265920
              }
            },
            "minValue": 0,
            "maxValue": 1265920,
            "observationCount": 122295,
            "timeSeriesCount": 11440
          }
        ],
        "observationCount": 122295,
        "timeSeriesCount": 11440
      },
      "dc/base/FBIGovCrime_AggCountry": {
        "importName": "FBIGovCrime_AggCountry",
        "seriesSummary": [
          {
            "seriesKey": {
              "observationPeriod": "P1Y",
              "isDcAggregate": true
            },
            "earliestDate": "2008",
            "latestDate": "2023",
            "placeTypeSummary": {
              "Country": {
                "placeCount": 1,
                "topPlaces": [
                  {
                    "dcid": "country/USA",
                    "name": "United States"
                  }
                ],
                "minValue": 7692556,
                "maxValue": 11111207
              }
            },
            "minValue": 7692556,
            "maxValue": 11111207,
            "observationCount": 15,
            "timeSeriesCount": 1
          }
        ],
        "observationCount": 15,
        "timeSeriesCount": 1
      }
    }
  }
}